loprop/__init__.py
loprop/__main__.py
loprop/core.py
loprop/dalton.py
loprop/veloxchem.py
LoProp-0.3.5.dist-info/LICENSE
LoProp-0.3.5.dist-info/METADATA
LoProp-0.3.5.dist-info/WHEEL
LoProp-0.3.5.dist-info/entry_points.txt
LoProp-0.3.5.dist-info/top_level.txt
LoProp-0.3.5.dist-info/RECORD
