Metadata-Version: 2.1
Name: LoProp
Version: 0.3.5
Summary: LoProp: localized molecular properties
Home-page: https://github.com/vahtras/loprop
Author: Olav Vahtras
Author-email: vahtras@kth.se
License: GPLv3
Platform: UNKNOWN
Classifier: Development Status :: 5 - Production/Stable
Classifier: Intended Audience :: Science/Research
Classifier: License :: OSI Approved :: GNU General Public License v3 (GPLv3)
Classifier: Programming Language :: Python
Classifier: Programming Language :: Python :: 3
Classifier: Programming Language :: Python :: 3.6
Classifier: Programming Language :: Python :: 3.7
Classifier: Programming Language :: Python :: 3.8
Classifier: Programming Language :: Python :: 3.9
Classifier: Topic :: Scientific/Engineering :: Chemistry
Requires-Dist: blocked-matrix-utils (>=1.0.8)
Provides-Extra: dalton
Requires-Dist: daltools (>=1.1.4) ; extra == 'dalton'
Provides-Extra: vlx
Requires-Dist: h5py ; extra == 'vlx'
